[
    {
        "id": 1,
        "slug": "automatisation-make",
        "title": "Boostez votre productivite avec Make",
        "description": "Decouvrez comment Make revolutionne les workflows d'entreprise en connectant vos applications favorites.",
        "imageSrc": "/images/linky-banner.png",
        "overlayImageSrc": "/images/mockup-make.png"
    },
    {
        "id": 2,
        "slug": "applications-glide",
        "title": "Creez des apps metier sans coder",
        "description": "Transformez vos Google Sheets en applications puissantes avec Glide.",
        "imageSrc": "/images/linky-banner.png",
        "overlayImageSrc": "/images/mockup-linky.png"
    },
    {
        "id": 3,
        "slug": "conseil-organisation",
        "title": "Organisez votre business plus rapidement",
        "description": "Decouvrez comment structurer et organiser votre entreprise pour gagner en efficacite.",
        "imageSrc": "/images/linky-banner.png",
        "overlayImageSrc": ""
    }
]